[
    {
        "title": "Chicken noodle soup",
        "description": "Mary Cadogan's aromatic broth will warm you up on a winter's evening - it contains ginger, which is particularly good for colds.",
        "time": "40 mins",
        "difficulty": "Easy",
        "vegan": false,
        "gluten_free": false
    },
    {
        "title": "Spiced carrot & lentil soup",
        "description": "A delicious, spicy blend packed full of iron and low in fat to boot. It's ready in under half an hour, or can be made in a slow cooker",
        "time": "25 mins",
        "difficulty": "Easy",
        "vegan": true,
        "gluten_free": true
    },
    {
        "title": "Celery soup",
        "description": "Cook up a batch of fresh, low-calorie celery soup for a healthy and filling veggie lunch or supper. Serve with chunks of crusty bread",
        "time": "55 mins",
        "difficulty": "Easy",
        "vegan": true,
        "gluten_free": true
    },
    {
        "title": "Tomato & basil soup",
        "description": "Combine fruity sundried tomatoes with tinned tomatoes to make this rich tomato soup with a homemade basil pesto \u2013 perfect for the depths of winter.",
        "time": "25 mins",
        "difficulty": "Easy",
        "vegan": false,
        "gluten_free": false
    },
    {
        "title": "Lentil soup",
        "description": "Enjoy this filling vegetarian soup with red lentils, carrots and leeks. It's low in calories and fat, and delivers three of your five-a-day ",
        "time": "1 hr 10 mins",
        "difficulty": "Easy",
        "vegan": true,
        "gluten_free": false
    },
    {
        "title": "Classic minestrone soup",
        "description": "Whip up this classic Italian vegetable soup with a rich tomato base and pasta. It's low in calories and packed with fibre and vitamin C",
        "time": "1 hr 5 mins",
        "difficulty": "Easy",
        "vegan": false,
        "gluten_free": false
    },
    {
        "title": "Butternut squash soup",
        "description": "Come in from the cold to a comforting bowl of autumnal squash soup. Adding a hint of chilli gives it a warming kick whilst cr\u00e8me fra\u00eeche makes it creamier",
        "time": "1 hr 5 mins",
        "difficulty": "Easy",
        "vegan": true,
        "gluten_free": false
    },
    {
        "title": "Versatile veg soup",
        "description": "Try a basic soup recipe that can be adapted for whatever veg you've got in the fridge. Serve with creme fraiche and fresh herbs",
        "time": "25 mins",
        "difficulty": "Easy",
        "vegan": true,
        "gluten_free": true
    },
    {
        "title": "Carrot & coriander soup",
        "description": "Everyone loves this super healthy soup, perfect for an easy supper",
        "time": "40 mins",
        "difficulty": "Easy",
        "vegan": true,
        "gluten_free": false
    },
    {
        "title": "Tomato soup",
        "description": "This warming vegan soup is made using juicy, ripe tomatoes, which come into season around September. It's a comforting recipe to make and eat throughout the year",
        "time": "1 hr 45 mins",
        "difficulty": "Easy",
        "vegan": true,
        "gluten_free": false
    },
    {
        "title": "Broccoli & stilton soup",
        "description": "A smooth, blended vegetable soup with blue cheese that's as good for a comforting meal as it is for a dinner party starter",
        "time": "45 mins",
        "difficulty": "Easy",
        "vegan": true,
        "gluten_free": false
    },
    {
        "title": "Tomato & pasta soup",
        "description": "Make our simple, budget-friendly tomato, pasta and chickpea soup in just 30 minutes. This easy, vegetarian family meal is healthy and even low fat",
        "time": "30 mins",
        "difficulty": "Easy",
        "vegan": true,
        "gluten_free": true
    },
    {
        "title": "Spiced lentil & butternut squash soup",
        "description": "Cook a big batch of this filling spiced lentil and squash soup and freeze the leftovers for a speedy supper another day. It's healthy and low in fat",
        "time": "50 mins",
        "difficulty": "Easy",
        "vegan": true,
        "gluten_free": true
    },
    {
        "title": "French onion soup",
        "description": "Our French onion soup is deliciously rich and easy to make at home. This savoury soup is perfect for using up a garden glut and great for dinner parties",
        "time": "1 hr 10 mins",
        "difficulty": "Easy",
        "vegan": false,
        "gluten_free": false
    },
    {
        "title": "Meatball & tomato soup",
        "description": "Get three of your 5-a-day in one serving with this healthy, low-calorie tomato soup. The addition of meatballs and giant couscous means it's filling, too",
        "time": "20 mins",
        "difficulty": "Easy",
        "vegan": true,
        "gluten_free": false
    },
    {
        "title": "Hearty pasta soup",
        "description": "Do something different with a pack of tortellini. This filling soup is full of fibre and veg, plus it's low in fat. The perfect lunch or supper",
        "time": "30 mins",
        "difficulty": "Easy",
        "vegan": true,
        "gluten_free": false
    },
    {
        "title": "Soup maker broccoli and stilton soup",
        "description": "Make a batch of classic broccoli and stilton soup with the help of a soup maker. It's freezable so you can make ahead for busy days, or a packed lunch",
        "time": "35 mins",
        "difficulty": "Easy",
        "vegan": true,
        "gluten_free": false
    },
    {
        "title": "Cauliflower soup",
        "description": "Throw together this comforting and creamy cauliflower soup for lunch or a light supper. It's perfect topped with parsley and served with crusty bread",
        "time": "40 mins",
        "difficulty": "Easy",
        "vegan": true,
        "gluten_free": true
    },
    {
        "title": "Leek, bacon & potato soup",
        "description": "This soup keeps well in the fridge and is easy to freeze",
        "time": "1 hr",
        "difficulty": "Easy",
        "vegan": false,
        "gluten_free": false
    },
    {
        "title": "Cheat's ramen noodle soup",
        "description": "Use chicken, ramen noodles, spinach, sweetcorn and eggs to make this warming soup, ideal for when you crave something comforting yet light and wholesome.",
        "time": "40 mins",
        "difficulty": "Easy",
        "vegan": false,
        "gluten_free": false
    },
    {
        "title": "Roasted sweet potato & carrot soup",
        "description": "This silky smooth, super versatile vegetarian soup is perfect for a dinner party starter, everyday dinner or warming lunch. Plus it's two of your five-a-day",
        "time": "50 mins",
        "difficulty": "Easy",
        "vegan": true,
        "gluten_free": false
    },
    {
        "title": "Courgette, potato & cheddar soup",
        "description": "This healthy low-calorie soup is a delicious way to use up courgettes when they're in season. Plus it's freezable, so you can make it in summer and enjoy all year",
        "time": "30 mins",
        "difficulty": "Easy",
        "vegan": true,
        "gluten_free": false
    },
    {
        "title": "Carrot & parsnip soup",
        "description": "Create a batch of creamy parsnip and carrot soup for a warming lunch or supper. Serve with crusty bread and freeze any leftovers you have for busy days",
        "time": "55 mins",
        "difficulty": "Easy",
        "vegan": true,
        "gluten_free": false
    },
    {
        "title": "Spicy chilli bean soup",
        "description": "There's minimal prep time to make this hearty bean soup, which works just as well as an easy dinner or packed in a flask for lunch",
        "time": "50 mins",
        "difficulty": "Easy",
        "vegan": true,
        "gluten_free": true
    },
    {
        "title": "Soup maker mushroom soup",
        "description": "Use a soup maker to make this easy, creamy mushroom soup. Chestnut or button mushrooms work well. Serve with crusty bread and freeze any leftovers ",
        "time": "35 mins",
        "difficulty": "Easy",
        "vegan": false,
        "gluten_free": false
    },
    {
        "title": "Mexican bean soup with guacamole",
        "description": "This warming, spiced vegetarian soup packs in goodness and is filling too. The quick-to-assemble guacamole topping tastes as good as it looks",
        "time": "30 mins",
        "difficulty": "Easy",
        "vegan": true,
        "gluten_free": true
    },
    {
        "title": "Pumpkin soup",
        "description": "Whip up this easy pumpkin soup as a starter for a dinner party or a light supper when you need a bit of comfort \u2013 it has a lovely silky texture",
        "time": "45 mins",
        "difficulty": "Easy",
        "vegan": true,
        "gluten_free": false
    },
    {
        "title": "Rustic vegetable soup",
        "description": "This vegetarian soup is packed with vegetables and lentils - it's healthy, low fat and full of flavour. To bulk it up, why not add borlotti beans or chicken?",
        "time": "45 mins",
        "difficulty": "Easy",
        "vegan": true,
        "gluten_free": true
    },
    {
        "title": "Chicken soup",
        "description": "Use up leftover chicken in this rustic soup with garlic yogurt. Best served with cheese scones",
        "time": "50 mins",
        "difficulty": "Easy",
        "vegan": false,
        "gluten_free": false
    },
    {
        "title": "Cabbage soup",
        "description": "Get three of your 5-a-day with a bowl of this healthy, low-fat cabbage soup. It's delicious on its own or served with a hunk of crusty, buttered bread",
        "time": "1 hr 10 mins",
        "difficulty": "Easy",
        "vegan": true,
        "gluten_free": true
    }
]